aws_apimatic/__init__.py
aws_apimatic/api_helper.py
aws_apimatic/aws_apimatic_client.py
aws_apimatic/configuration.py
aws_apimatic/decorators.py
aws_apimatic/controllers/__init__.py
aws_apimatic/controllers/awse_commerce_service_binding_controller.py
aws_apimatic/controllers/base_controller.py
aws_apimatic/exceptions/__init__.py
aws_apimatic/exceptions/api_exception.py
aws_apimatic/http/__init__.py
aws_apimatic/http/http_call_back.py
aws_apimatic/http/http_client.py
aws_apimatic/http/http_context.py
aws_apimatic/http/http_method_enum.py
aws_apimatic/http/http_request.py
aws_apimatic/http/http_response.py
aws_apimatic/http/requests_client.py
aws_apimatic/models/__init__.py
aws_apimatic/models/accessories.py
aws_apimatic/models/accessory.py
aws_apimatic/models/action_enum.py
aws_apimatic/models/alternate_version.py
aws_apimatic/models/alternate_versions.py
aws_apimatic/models/ancestors.py
aws_apimatic/models/argument.py
aws_apimatic/models/arguments.py
aws_apimatic/models/audience_rating_enum.py
aws_apimatic/models/availability_attributes.py
aws_apimatic/models/availability_enum.py
aws_apimatic/models/bin.py
aws_apimatic/models/bin_parameter.py
aws_apimatic/models/browse_node.py
aws_apimatic/models/browse_node_lookup_request.py
aws_apimatic/models/browse_nodes.py
aws_apimatic/models/cart_add_request.py
aws_apimatic/models/cart_clear_request.py
aws_apimatic/models/cart_create_request.py
aws_apimatic/models/cart_get_request.py
aws_apimatic/models/cart_modify_request.py
aws_apimatic/models/catalog_number_list.py
aws_apimatic/models/children.py
aws_apimatic/models/collection.py
aws_apimatic/models/collection_item.py
aws_apimatic/models/collection_parent.py
aws_apimatic/models/collection_summary.py
aws_apimatic/models/collections.py
aws_apimatic/models/condition_enum.py
aws_apimatic/models/corrected_query.py
aws_apimatic/models/creator.py
aws_apimatic/models/customer_reviews.py
aws_apimatic/models/decimal_with_units.py
aws_apimatic/models/disc.py
aws_apimatic-1.0.dist-info/LICENSE
aws_apimatic-1.0.dist-info/METADATA
aws_apimatic-1.0.dist-info/WHEEL
aws_apimatic-1.0.dist-info/top_level.txt
aws_apimatic-1.0.dist-info/RECORD
